integrations/__init__.py
integrations/github/__init__.py
integrations/github/github.py
integrations/github/models.py
integrations/github/search.py
tools/__init__.py
tools/codeql/__init__.py
tools/codeql/codeql_runner.py
tools/semgrep/__init__.py
tools/semgrep/results_db.py
tools/semgrep/semgrep_runner.py
tools/semgrep/rules/tarslip.yaml
models.py
scanipy.py
scanipy_cli-0.1.0.dist-info/METADATA
scanipy_cli-0.1.0.dist-info/WHEEL
scanipy_cli-0.1.0.dist-info/entry_points.txt
scanipy_cli-0.1.0.dist-info/licenses/LICENSE
scanipy_cli-0.1.0.dist-info/RECORD
