Metadata-Version: 2.4
Name: scanipy-cli
Version: 0.1.0
Summary: A powerful CLI tool to scan GitHub repositories for security patterns and vulnerabilities
Project-URL: Homepage, https://github.com/papadoxie/scanipy
Project-URL: Documentation, https://papadoxie.github.io/scanipy/
Project-URL: Repository, https://github.com/papadoxie/scanipy
Project-URL: Issues, https://github.com/papadoxie/scanipy/issues
Project-URL: Changelog, https://github.com/papadoxie/scanipy/blob/main/CHANGELOG.md
Author-email: papadoxie <papadoxie@users.noreply.github.com>
License: MIT
License-File: LICENSE
Keywords: code-search,codeql,github,sast,security,semgrep,static-analysis,vulnerability
Classifier: Development Status :: 4 - Beta
Classifier: Environment :: Console
Classifier: Intended Audience :: Developers
Classifier: Intended Audience :: Information Technology
Classifier: Intended Audience :: Science/Research
Classifier: License :: OSI Approved :: MIT License
Classifier: Operating System :: OS Independent
Classifier: Programming Language :: Python :: 3
Classifier: Programming Language :: Python :: 3.12
Classifier: Programming Language :: Python :: 3.13
Classifier: Topic :: Security
Classifier: Topic :: Software Development :: Quality Assurance
Classifier: Topic :: Software Development :: Testing
Classifier: Typing :: Typed
Requires-Python: >=3.12
Requires-Dist: colorama>=0.4.6
Requires-Dist: python-dotenv>=1.0.0
Requires-Dist: requests>=2.31.0
Provides-Extra: dev
Requires-Dist: mypy>=1.8.0; extra == 'dev'
Requires-Dist: pytest-cov>=4.1.0; extra == 'dev'
Requires-Dist: pytest>=8.0.0; extra == 'dev'
Requires-Dist: ruff>=0.1.0; extra == 'dev'
Requires-Dist: types-requests>=2.31.0; extra == 'dev'
Provides-Extra: docs
Requires-Dist: mkdocs-material>=9.5.0; extra == 'docs'
Requires-Dist: mkdocs>=1.5.0; extra == 'docs'
